LICENSE
MANIFEST.in
README.rst
setup.py
contextvars/__init__.py
contextvars.egg-info/PKG-INFO
contextvars.egg-info/SOURCES.txt
contextvars.egg-info/dependency_links.txt
contextvars.egg-info/top_level.txt
tests/__init__.py
tests/test_basics.py