Metadata-Version: 1.1
Name: contextvars
Version: 2.0
Summary: PEP 567 Backport
Home-page: UNKNOWN
Author: MagicStack Inc
Author-email: hello@magic.io
License: Apache License, Version 2.0
Platform: UNKNOWN
Classifier: Development Status :: 3 - Alpha
Classifier: Programming Language :: Python :: 3 :: Only
Classifier: Programming Language :: Python :: 3.6
Classifier: Operating System :: POSIX
Classifier: Operating System :: MacOS :: MacOS X
Classifier: Operating System :: Microsoft :: Windows
Classifier: License :: OSI Approved :: Apache Software License
Classifier: Intended Audience :: Developers
Provides: contextvars
